HISTORY.md
couchutils/__init__.py
couchutils/compile_doc.py
couchutils-0.5.0.dist-info/LICENSE.txt
couchutils-0.5.0.dist-info/METADATA
couchutils-0.5.0.dist-info/WHEEL
couchutils-0.5.0.dist-info/RECORD
