Metadata-Version: 2.1
Name: couchutils
Version: 0.5.0
Summary: A collection of CouchDB utils.
Home-page: https://github.com/rwanyoike/couchutils-python
License: MIT
Author: Raymond Wanyoike
Author-email: raymond.wanyoike@gmail.com
Requires-Python: >=3.8,<4.0
Classifier: License :: OSI Approved :: MIT License
Classifier: Programming Language :: Python :: 3
Classifier: Programming Language :: Python :: 3.8
Classifier: Programming Language :: Python :: 3.9
Classifier: Programming Language :: Python :: 3.10
Classifier: Programming Language :: Python :: 3.11
Classifier: Programming Language :: Python :: 3.12
Project-URL: Documentation, https://github.com/rwanyoike/couchutils-python/tree/main/docs
Project-URL: Repository, https://github.com/rwanyoike/couchutils-python
